consts/__init__.py
consts/consts.py
infi_azure/__init__.py
infi_azure/azcopy.py
infi_azure/blob.py
infi_azure/container.py
infi_azure/storage_account.py
tests/__init__.py
tests/azcopy.py
tests/blob.py
tests/container.py
tests/storage_account.py
tests/test_config.py
infi_azure-0.0.9.dist-info/METADATA
infi_azure-0.0.9.dist-info/WHEEL
infi_azure-0.0.9.dist-info/top_level.txt
infi_azure-0.0.9.dist-info/RECORD
