Metadata-Version: 2.1
Name: infi-azure
Version: 0.0.9
Summary: Azure python package for infinity team
Author: Infinity Team
License: MIT
Requires-Dist: azure.storage.blob ==12.19.*
Requires-Dist: pytest ==7.4.*
